dalec_openproject/__init__.py
dalec_openproject/apps.py
dalec_openproject/proxy.py
dalec_openproject-0.1.0.dist-info/AUTHORS
dalec_openproject-0.1.0.dist-info/LICENSE
dalec_openproject-0.1.0.dist-info/METADATA
dalec_openproject-0.1.0.dist-info/WHEEL
dalec_openproject-0.1.0.dist-info/top_level.txt
dalec_openproject-0.1.0.dist-info/RECORD
