Metadata-Version: 2.1
Name: dalec-openproject
Version: 0.1.0
Summary: Dalec plugin to retrieve openproject data
Home-page: https://github.com/webu/dalec-openproject
Author: Webu
Author-email: contact@webu.coop
License: BSD-3-Clause
Project-URL: Source, https://github.com/webu/dalec-openproject
Project-URL: Tracker, https://github.com/webu/dalec-openproject/issues
Classifier: Development Status :: 5 - Production/Stable
Classifier: Environment :: Web Environment
Classifier: Framework :: Django
Classifier: Intended Audience :: Developers
Classifier: License :: OSI Approved :: BSD License
Classifier: Operating System :: OS Independent
Classifier: Programming Language :: Python
Classifier: Programming Language :: Python :: 3
Classifier: Topic :: Internet :: WWW/HTTP
Classifier: Topic :: Internet :: WWW/HTTP :: Dynamic Content
Classifier: Topic :: Software Development :: Libraries :: Application Frameworks
Classifier: Topic :: Software Development :: Libraries :: Python Modules
Requires-Python: >=3.7
License-File: LICENSE
License-File: AUTHORS
Requires-Dist: Django (>=2.2)
Requires-Dist: dalec
Requires-Dist: pyopenproject
